adfluo/__init__.py
adfluo/cache.py
adfluo/cli.py
adfluo/dataset.py
adfluo/exceptions.py
adfluo/extraction_graph.py
adfluo/extractor.py
adfluo/pipeline.py
adfluo/processors.py
adfluo/storage.py
adfluo/types.py
adfluo/utils.py
adfluo/validator.py
adfluo/plots/__init__.py
adfluo/plots/sphinx_utils.py
adfluo/plots/svg_rendering.py
adfluo-0.4.2.dist-info/LICENSE
adfluo-0.4.2.dist-info/METADATA
adfluo-0.4.2.dist-info/WHEEL
adfluo-0.4.2.dist-info/entry_points.txt
adfluo-0.4.2.dist-info/top_level.txt
adfluo-0.4.2.dist-info/RECORD
