Metadata-Version: 2.1
Name: adfluo
Version: 0.4.2
Summary: Pipeline-oriented feature extraction for multimodal datasets
Author-email: Hadrien Titeux <hadrien.titeux@ens.psl.eu>
License: EUPL
Classifier: Development Status :: 3 - Alpha
Classifier: License :: OSI Approved :: MIT License
Classifier: Intended Audience :: Developers
Classifier: Intended Audience :: Science/Research
Classifier: Programming Language :: Python :: 3.10
Classifier: Programming Language :: Python :: 3.11
Classifier: Programming Language :: Python :: 3.12
Requires-Python: >=3.10
License-File: LICENSE
Requires-Dist: rich
Requires-Dist: tqdm
Requires-Dist: sortedcontainers >=2.3.0
Provides-Extra: docs
Requires-Dist: sphinx ; extra == 'docs'
Requires-Dist: sphinx-rtd-theme ; extra == 'docs'
Provides-Extra: plots
Requires-Dist: CairoSVG ; extra == 'plots'
Requires-Dist: drawsvg >=2.3.0 ; extra == 'plots'
Requires-Dist: grandalf >=0.8 ; extra == 'plots'
Provides-Extra: tests
Requires-Dist: pytest ; extra == 'tests'
Requires-Dist: pandas ; extra == 'tests'
Requires-Dist: CairoSVG ; extra == 'tests'
Requires-Dist: drawsvg >=2.3.0 ; extra == 'tests'
Requires-Dist: grandalf >=0.8 ; extra == 'tests'
